README.md
setup.py
icpv/__init__.py
icpv.egg-info/PKG-INFO
icpv.egg-info/SOURCES.txt
icpv.egg-info/dependency_links.txt
icpv.egg-info/requires.txt
icpv.egg-info/top_level.txt