Metadata-Version: 2.1
Name: icpv
Version: 0.0.0a0
Summary: Integrated Circuit Physical Verification
Home-page: https://github.com/yeungchie/icpv
Author: YEUNGCHIE
Keywords: icpv,verification,virtuoso,calibre,python,linux,yeungchie
Classifier: Development Status :: 3 - Alpha
Classifier: Intended Audience :: Developers
Classifier: Programming Language :: Python :: 3
Classifier: Programming Language :: Python :: 3.7
Classifier: Programming Language :: Python :: 3.8
Classifier: Programming Language :: Python :: 3.12
Classifier: License :: OSI Approved :: GNU Affero General Public License v3
Classifier: Operating System :: Unix
Requires-Python: >=3.7
Requires-Dist: typing_extensions
Requires-Dist: PyYAML
Requires-Dist: numpy
Requires-Dist: gdstk
